{
  "key_name": "devops2-key",
  "pem_file": "devops2-key.pem",
  "dynamo_table": "devops-nodes",
  "nat_eip_alloc_id": "eipalloc-0afecfb9426056111",
  "nat_gateway_id": "nat-0ab83f9996fae8be2",
  "vpc_id": "vpc-0ce7f583bfc192ed9",
  "igw_id": "igw-0ca3610bfa0f8dc6e",
  "public_subnet_ids": [
    "subnet-00258dab6518e14ef",
    "subnet-0bbe687ced0abbfad"
  ],
  "private_subnet_ids": [
    "subnet-01059298c16763720",
    "subnet-0a053936775127097"
  ],
  "public_rt_id": "rtb-06d2f5e669cf39afb",
  "private_rt_id": "rtb-02019fc025f02a7f9"
}